openfisca_us_data/__init__.py
openfisca_us_data/cli.py
openfisca_us_data/utils.py
openfisca_us_data/datasets/__init__.py
openfisca_us_data/datasets/acs/__init__.py
openfisca_us_data/datasets/acs/acs.py
openfisca_us_data/datasets/acs/raw_acs.py
openfisca_us_data/datasets/ce/__init__.py
openfisca_us_data/datasets/ce/ce.py
openfisca_us_data/datasets/ce/raw_ce.py
openfisca_us_data/datasets/cps/__init__.py
openfisca_us_data/datasets/cps/cps.py
openfisca_us_data/datasets/cps/raw_cps.py
openfisca_us_data-0.1.4.dist-info/METADATA
openfisca_us_data-0.1.4.dist-info/WHEEL
openfisca_us_data-0.1.4.dist-info/entry_points.txt
openfisca_us_data-0.1.4.dist-info/top_level.txt
openfisca_us_data-0.1.4.dist-info/RECORD
